nixy/__init__.py
nixy-0.1.0.dist-info/LICENSE
nixy-0.1.0.dist-info/WHEEL
nixy-0.1.0.dist-info/METADATA
nixy-0.1.0.dist-info/RECORD
