Metadata-Version: 2.1
Name: nixy
Version: 0.1.0
Summary: Python bindings for Nix package manager and nix-user-chroot
License: Apache-2.0
Author: Anna Rogers
Author-email: arogers@sodas.ku.dk
Requires-Python: >=3.8,<4.0
Classifier: Development Status :: 1 - Planning
Classifier: License :: OSI Approved :: Apache Software License
Classifier: Programming Language :: Python :: 3
Classifier: Programming Language :: Python :: 3.8
Classifier: Programming Language :: Python :: 3.9
Requires-Dist: typer (>=0.3.2,<0.4.0)
